termflow/__init__.py
termflow/__main__.py
termflow-0.1.0.dist-info/LICENSE
termflow-0.1.0.dist-info/METADATA
termflow-0.1.0.dist-info/WHEEL
termflow-0.1.0.dist-info/entry_points.txt
termflow-0.1.0.dist-info/top_level.txt
termflow-0.1.0.dist-info/RECORD
